{"cameraMode":{"drawMode":0,"name":"Shaded","section":"Shading Mode"},"sceneLighting":false,"audioPlay":false,"sceneViewState":{"showFog":true,"showMaterialUpdate":true,"showSkybox":false,"showFlares":false,"showImageEffects":true,"showParticleSystems":false,"showVisualEffectGraphs":true,"m_FxEnabled":true},"in2DMode":false,"pivot":{"x":67.0713119506836,"y":88.94377899169922,"z":-73.78536987304688},"rotation":{"x":-0.0371534526348114,"y":0.21570530533790589,"z":0.008399038575589657,"w":0.9758040308952332},"size":77.21783447265625,"orthographic":false}